rxn/onmt_models/__init__.py
rxn/onmt_models/augmentation.py
rxn/onmt_models/defaults.py
rxn/onmt_models/prediction_collapser.py
rxn/onmt_models/prediction_utils.py
rxn/onmt_models/py.typed
rxn/onmt_models/training_files.py
rxn/onmt_models/translation.py
rxn/onmt_models/utils.py
rxn/onmt_models/scripts/__init__.py
rxn/onmt_models/scripts/rxn_onmt_augment.py
rxn/onmt_models/scripts/rxn_onmt_continue_training.py
rxn/onmt_models/scripts/rxn_onmt_finetune.py
rxn/onmt_models/scripts/rxn_onmt_preprocess.py
rxn/onmt_models/scripts/rxn_onmt_strip_checkpoints.py
rxn/onmt_models/scripts/rxn_onmt_train.py
rxn/onmt_models/scripts/rxn_plan_training.py
rxn/onmt_models/scripts/rxn_prepare_data.py
rxn/onmt_models/scripts/rxn_translate.py
rxn_onmt_models-1.1.0.dist-info/LICENSE
rxn_onmt_models-1.1.0.dist-info/METADATA
rxn_onmt_models-1.1.0.dist-info/WHEEL
rxn_onmt_models-1.1.0.dist-info/entry_points.txt
rxn_onmt_models-1.1.0.dist-info/top_level.txt
rxn_onmt_models-1.1.0.dist-info/RECORD
