Metadata-Version: 2.1
Name: rxn-onmt-models
Version: 1.1.0
Summary: Training of OpenNMT-based RXN models
Home-page: https://github.com/rxn4chemistry/rxn-onmt-models
Author: IBM RXN team
License: MIT
Project-URL: Documentation, https://rxn4chemistry.github.io/rxn-onmt-models/
Project-URL: Repository, https://github.com/rxn4chemistry/rxn-onmt-models
Classifier: Operating System :: OS Independent
Classifier: Programming Language :: Python :: 3
Classifier: Programming Language :: Python :: 3.6
Classifier: Programming Language :: Python :: 3.7
Classifier: Programming Language :: Python :: 3.8
Requires-Python: >=3.6
License-File: LICENSE
Requires-Dist: attrs >=21.2.0
Requires-Dist: click >=8.0
Requires-Dist: rxn-chem-utils >=1.1.4
Requires-Dist: rxn-onmt-utils >=1.0.3
Requires-Dist: rxn-reaction-preprocessing >=2.0.2
Requires-Dist: rxn-utils >=1.1.9
Provides-Extra: dev
Requires-Dist: black >=22.3.0 ; extra == 'dev'
Requires-Dist: bump2version >=1.0.1 ; extra == 'dev'
Requires-Dist: flake8 >=3.8.4 ; extra == 'dev'
Requires-Dist: freezegun >=1.1.2 ; extra == 'dev'
Requires-Dist: isort >=5.10.1 ; extra == 'dev'
Requires-Dist: mypy >=0.910 ; extra == 'dev'
Requires-Dist: pytest >=5.3.4 ; extra == 'dev'
Requires-Dist: types-setuptools >=57.4.14 ; extra == 'dev'
Provides-Extra: rdkit
Requires-Dist: rdkit-pypi >=2021.3.2 ; (python_version < "3.7") and extra == 'rdkit'
Requires-Dist: rdkit >=2022.3.4 ; (python_version >= "3.7") and extra == 'rdkit'
